pipen_board/__init__.py
pipen_board/additional_auto.toml
pipen_board/apis.py
pipen_board/cli.py
pipen_board/data_manager.py
pipen_board/defaults.py
pipen_board/frontend/build/assets/favicon-running.png
pipen_board/frontend/build/assets/favicon.png
pipen_board/frontend/build/assets/index.css
pipen_board/frontend/build/assets/index.js
pipen_board/frontend/build/assets/schema.json
pipen_board/frontend/build/index.html
pipen_board/plugin.py
pipen_board/quart_app.py
pipen_board/version.py
pipen_board-1.1.0.dist-info/METADATA
pipen_board-1.1.0.dist-info/WHEEL
pipen_board-1.1.0.dist-info/entry_points.txt
pipen_board-1.1.0.dist-info/RECORD
