Metadata-Version: 2.4
Name: pipen-board
Version: 1.1.0
Summary: Visualization configuration and running of pipen pipelines on the web
License: MIT
Author: pwwang
Author-email: pwwang@pwwang.com
Requires-Python: >=3.9,<4.0
Classifier: License :: OSI Approved :: MIT License
Classifier: Programming Language :: Python :: 3
Classifier: Programming Language :: Python :: 3.9
Classifier: Programming Language :: Python :: 3.10
Classifier: Programming Language :: Python :: 3.11
Classifier: Programming Language :: Python :: 3.12
Classifier: Programming Language :: Python :: 3.13
Classifier: Programming Language :: Python :: 3.14
Provides-Extra: all
Provides-Extra: diagram
Provides-Extra: filters
Provides-Extra: report
Requires-Dist: pipen-args (>=1.1,<2.0)
Requires-Dist: pipen-diagram (>=1.1,<2.0) ; extra == "diagram" or extra == "all"
Requires-Dist: pipen-filters (>=1.1,<2.0) ; extra == "filters" or extra == "all"
Requires-Dist: pipen-log2file (>=1.1,<2.0)
Requires-Dist: pipen-report (>=1.1,<2.0) ; extra == "report" or extra == "all"
Requires-Dist: psutil (>=7,<8)
Requires-Dist: python-slugify (>=8.0,<9.0)
Requires-Dist: quart (>=0.20,<0.21)
Requires-Dist: taskgroup (>=0.2,<0.3) ; python_version < "3.11"
Requires-Dist: websocket-client (>=1.8,<2.0)
